todo_cli/Storage.py
todo_cli/Task.py
todo_cli/TaskService.py
todo_cli/TaskView.py
todo_cli/__init__.py
todo_cli/main.py
todo_cli_kyra_pure_python-0.1.dist-info/METADATA
todo_cli_kyra_pure_python-0.1.dist-info/WHEEL
todo_cli_kyra_pure_python-0.1.dist-info/entry_points.txt
todo_cli_kyra_pure_python-0.1.dist-info/top_level.txt
todo_cli_kyra_pure_python-0.1.dist-info/RECORD
