Metadata-Version: 2.4
Name: todo_cli_kyra_pure_python
Version: 0.1
Summary: A command line todo tool
Home-page: https://gitee.com/a1_dong-ry/todo_cli
Author: kyra
Author-email: kyra <m13409971925@163.com>
License: MIT
Classifier: Development Status :: 4 - Beta
Classifier: Intended Audience :: End Users/Desktop
Classifier: Topic :: Utilities
Classifier: License :: OSI Approved :: MIT License
Classifier: Programming Language :: Python :: 3
Classifier: Programming Language :: Python :: 3.7
Classifier: Programming Language :: Python :: 3.8
Classifier: Programming Language :: Python :: 3.9
Classifier: Programming Language :: Python :: 3.10
Classifier: Programming Language :: Python :: 3.11
Classifier: Operating System :: OS Independent
Requires-Python: >=3.6
Requires-Dist: click>=8.1.3
Requires-Dist: fuzzywuzzy>=0.18.0
Requires-Dist: jieba>=0.42.1
Requires-Dist: tabulate>=0.9.0
Requires-Dist: python-dateutil>=2.8.2
Requires-Dist: dataclasses>=0.8; python_version < "3.7"
Provides-Extra: visualization
Requires-Dist: matplotlib>=3.7.1; extra == "visualization"
Requires-Dist: wordcloud>=1.8.2.2; extra == "visualization"
Provides-Extra: notification
Requires-Dist: plyer>=2.0.0; extra == "notification"
Provides-Extra: dev
Requires-Dist: pytest>=7.3.1; extra == "dev"
Requires-Dist: flake8>=6.0.0; extra == "dev"
Requires-Dist: black>=23.3.0; extra == "dev"
Requires-Dist: isort>=5.12.0; extra == "dev"
Provides-Extra: docs
Requires-Dist: sphinx>=6.2.1; extra == "docs"
Requires-Dist: sphinx-rtd-theme>=1.2.0; extra == "docs"
Dynamic: author
Dynamic: home-page
Dynamic: requires-python
